pyems/__init__.py
pyems/protocols.py
pyems/utils.py
pyems-0.1.2.dist-info/DESCRIPTION.rst
pyems-0.1.2.dist-info/METADATA
pyems-0.1.2.dist-info/RECORD
pyems-0.1.2.dist-info/WHEEL
pyems-0.1.2.dist-info/metadata.json
pyems-0.1.2.dist-info/top_level.txt
